[
  {
    "variation": "default",
    "name": "Default",
    "slice_type": "posts",
    "items": [],
    "primary": {
      "title": [
        {
          "type": "heading1",
          "text": "Revolutionize clicks-and-mortar deliverables",
          "spans": []
        }
      ],
      "description": [
        {
          "type": "paragraph",
          "text": "Labore voluptate proident aliqua est aute nostrud duis aliqua reprehenderit deserunt nisi ad. Cupidatat velit irure aute anim aute et nostrud duis Lorem aliquip.",
          "spans": []
        }
      ]
    }
  }
]